sillywalk/__init__.py
sillywalk/_mlpca.py
sillywalk/anybody.py
sillywalk/templates/model.any.jinja
sillywalk/version.py
sillywalk-1.1.1.dist-info/licenses/LICENSE
sillywalk-1.1.1.dist-info/WHEEL
sillywalk-1.1.1.dist-info/METADATA
sillywalk-1.1.1.dist-info/RECORD
