Metadata-Version: 2.4
Name: sillywalk
Version: 1.1.1
Summary: Library for maximum likelihood principal component analysis for AnyBody models
Author: Morten Enemark Lund
Author-email: Morten Enemark Lund <melund@gmail.com>
License-Expression: MIT
License-File: LICENSE
Classifier: Programming Language :: Python :: 3
Classifier: Programming Language :: Python :: 3.11
Classifier: Programming Language :: Python :: 3.12
Classifier: Programming Language :: Python :: 3.13
Requires-Dist: numpy
Requires-Dist: jinja2
Requires-Dist: scikit-learn
Requires-Dist: narwhals
Requires-Python: >=3.11
Project-URL: repository, https://github.com/AnyBody-Research-Group/sillywalk
